setup.py
tle.egg-info/PKG-INFO
tle.egg-info/SOURCES.txt
tle.egg-info/dependency_links.txt
tle.egg-info/not-zip-safe
tle.egg-info/top_level.txt
tle_proj/__init__.py
tle_proj/tests.py
tle_proj/tle_calc.py