Metadata-Version: 1.0
Name: tle
Version: 0.1
Summary: tle functions
Home-page: UNKNOWN
Author: John Doe
Author-email: UNKNOWN
License: UNKNOWN
Platform: UNKNOWN
